confound_prediction/__init__.py
confound_prediction/data_simulation.py
confound_prediction/deconfounding.py
confound_prediction/mutual_information.py
confound_prediction/prediction.py
confound_prediction/sampling.py
confound_prediction/utils.py
confound_prediction/test/__init__.py
confound_prediction/test/do_clear.py
confound_prediction/test/test_deconfounding.py
confound_prediction/test/test_mutual_information.py
confound_prediction/test/test_sampling.py
confound_prediction/test/test_simulate_data.py
confound_prediction/test/test_utils.py
confound_prediction-0.0.1a1.dist-info/LICENSE.txt
confound_prediction-0.0.1a1.dist-info/METADATA
confound_prediction-0.0.1a1.dist-info/WHEEL
confound_prediction-0.0.1a1.dist-info/top_level.txt
confound_prediction-0.0.1a1.dist-info/RECORD
