Metadata-Version: 2.1
Name: confound-prediction
Version: 0.0.1a1
Summary: Confound-isolating cross-validation approach to control for a confounding effect in a predictive model.
Home-page: https://github.com/darya-chyzhyk/confound_prediction
Author: Darya Chyzhyk
Author-email: darya.chyzhyk@gmail.com
License: UNKNOWN
Platform: any
Classifier: Programming Language :: Python :: 3.5
Classifier: Programming Language :: Python :: 3.6
Classifier: License :: OSI Approved :: BSD License
Classifier: Operating System :: OS Independent
Classifier: Topic :: Scientific/Engineering
Requires-Dist: scipy (>=1.1.0)
Requires-Dist: scikit-learn (>=0.21.2)
Requires-Dist: numpy (>=1.14.2)
